MANIFEST.in
README.rst
setup.py
ml8/__init__.py
ml8/base.py
ml8.egg-info/PKG-INFO
ml8.egg-info/SOURCES.txt
ml8.egg-info/dependency_links.txt
ml8.egg-info/requires.txt
ml8.egg-info/top_level.txt
ml8/classifier/__init__.py
ml8/classifier/dt_tree.py
ml8/classifier/knn_model.py
ml8/cv/__init__.py
ml8/cv/demo_face_matching/__init__.py
ml8/cv/demo_face_matching/tf_face.py
ml8/cv/demo_face_matching/tf_face_conv.py
ml8/datasets/__init__.py
ml8/datasets/base.py
ml8/datasets/model_selection.py
ml8/datasets/preprocessing.py
ml8/datasets/TSNE/TSNEView.py
ml8/datasets/TSNE/__init__.py
ml8/datasets/data/README.md
ml8/datasets/data/boston.csv
ml8/datasets/data/boston.py
ml8/datasets/data/boston.rst
ml8/datasets/data/iris.csv
ml8/datasets/data/iris.json
ml8/datasets/data/iris.py
ml8/datasets/data/iris.rst
ml8/datasets/data/result.txt
ml8/datasets/tests/__init__.py
ml8/example/__init__.py
ml8/example/base.py
ml8/example/demo_gan.py
ml8/example/demo_joke.py
ml8/example/demo_neural_style.py
ml8/example/demo_news.py
ml8/example/demos.py
ml8/example/demo_face_matching/__init__.py
ml8/example/demo_face_matching/tf_face.py
ml8/example/demo_face_matching/tf_face_conv.py
ml8/example/demo_iris/__init__.py
ml8/example/demo_iris/demo_iris.py
ml8/example/demo_iris/tests.py
ml8/metrics/__init__.py
ml8/metrics/classification.py
ml8/utils/__init__.py
ml8/utils/tools.py